ttaat/__init__.py
ttaat/cli.py
ttaat/db.py
ttaat/mcp.py
ttaat/version.py
ttaat-0.1.6.dist-info/METADATA
ttaat-0.1.6.dist-info/WHEEL
ttaat-0.1.6.dist-info/entry_points.txt
ttaat-0.1.6.dist-info/licenses/LICENSE
ttaat-0.1.6.dist-info/RECORD
