Metadata-Version: 2.4
Name: ttaat
Version: 0.1.6
Summary: Two Truths and a Twist: A trivia game for users of AI
Author-email: moorkh <moorkh@ergodic.xyz>
License-File: LICENSE
Requires-Python: >=3.13
Requires-Dist: mcp[cli]>=1.6.0
Requires-Dist: platformdirs>=4.0.0
